uart_tx/uart_tx.vhd
library ieee;
  use ieee.std_logic_1164.all;
  use ieee.numeric_std.all;

entity uart_tx is
    generic (
        DATA_BITS    : integer := 8;
        CLK_FREQ     : integer := 115200;  -- frequency of FPGA
        BAUD_RATE    : integer := 115200   -- Uart frequency
    );
    port (
        clk_i      : in  std_logic;
        rst_i      : in  std_logic;
        data_i     : in std_logic_vector((DATA_BITS-1) downto 0);
        tx_o       : out  std_logic;
        tx_order_i : in std_logic;
        tx_busy_o  : out std_logic
    );
end entity uart_tx;

architecture rtl_uart_tx of uart_tx is

     -- latch to save data_i while doing UART transactions
    signal b : std_logic_vector((DATA_BITS-1) downto 0);

    -- CLK_FREQ / BAUD_RATE = Clk hits per bit being sent
    constant CLKS_PER_BIT : integer := CLK_FREQ / BAUD_RATE; -- 1 hit / bit

    signal clk_count : integer range 0 to CLKS_PER_BIT - 1;
    signal bit_count : integer range 0 to DATA_BITS+2;

    --flags
    signal frame_sent : std_logic; --flag to know if dataframe has been sent before tx_order reset
    signal is_busy : std_logic;    -- flag to know if component is busy
    signal b_saved : std_logic;    --flag to know if data has been saved in latch
begin

tx_busy_o <= is_busy;
process(clk_i, rst_i)
begin
    if rst_i = '1' then --reset system
        tx_o <= '1';
        is_busy <= '0';
        --internal signals
        b <= (others => '0');
        b_saved <= '0';
        clk_count <= 0 ;
        bit_count <= 0;
        frame_sent <= '0';

        
    elsif rising_edge(clk_i) then
        -- FRAME State : Nothing to send, nothing is being sent
            if (tx_order_i = '0') and (frame_sent = '0') and (is_busy = '0') then
                --Reset for next UART Tx
                b <= (others => '0');
                b_saved <= '0';
                clk_count <= 0 ;
                bit_count <= 0;
        -- FRAME State : Frame isn't being sent/already sent, received order
            elsif (tx_order_i = '1') and (frame_sent = '0') and (is_busy = '0') then
                if b_saved = '0' then
                    b <= data_i; --saving data in a latch for safety as anything can happen to data_i
                    b_saved <= '1';
                    is_busy <= '1'; --starting Tx
                end if ;

        -- FRAME State : Frame is being sent
            elsif (is_busy = '1') and (frame_sent = '0') then
                -- Sending i-th bit
                if clk_count < CLKS_PER_BIT -1 then -- CLKS_PER_BIT = 1
                    clk_count <= clk_count + 1;

                else 
                    if bit_count = 0 then   
                        tx_o <= '0'; --START bit
                        bit_count <= bit_count +1;
                    
                    elsif bit_count < DATA_BITS + 1 then --"START + DATA" = DATA_BITS + 1 
                        tx_o <= b(bit_count-1);
                        bit_count <= bit_count + 1;
                        

                    elsif bit_count < DATA_BITS + 2 then --"START + DATA + STOP" = DATA_BITS + 2
                        tx_o <= '1'; --STOP bit
                        bit_count <= bit_count + 1;
                    else
                        frame_sent <= '1';

                    end if;
                clk_count <= 0; --reset for next bit

                end if;
        -- FRAME State : Already sent, waiting for tx_order_i reset
        -- for safety do not release busy flag here
            elsif (tx_order_i = '1') and (frame_sent = '1') and (is_busy = '1') then
                --Reset for next UART Tx
                b <= (others => '0');
                b_saved <= '0';
                clk_count <= 0 ;
                bit_count <= 0;

        -- FRAME State : Already sent, tx_order_i was resetted 
        -- => can reset frame_sent safely and release busy flag
            elsif (tx_order_i = '0') and (frame_sent = '1') and (is_busy = '1') then
                frame_sent <= '0';
                is_busy <= '0';
                --Reset for next UART Tx
                b <= (others => '0');
                b_saved <= '0';
                clk_count <= 0 ;
                bit_count <= 0;
            end if;

    end if;

end process;

end architecture rtl_uart_tx;

uart_tx/simulation_test_uart_tx_sanity_check.vcd
$date
  Sat Apr 18 22:00:18 2026
$end
$version
  GHDL v0
$end
$timescale
  1 ps
$end
$scope module standard $end
$upscope $end
$scope module std_logic_1164 $end
$upscope $end
$scope module numeric_std $end
$upscope $end
$scope module uart_tx $end
$var reg 1 ! clk_i $end
$var reg 1 " rst_i $end
$var reg 12 # data_i[11:0] $end
$var reg 1 $ tx_o $end
$var reg 1 % tx_order_i $end
$var reg 1 & tx_busy_o $end
$var reg 12 ' b[11:0] $end
$var integer 32 ( bit_count $end
$var reg 1 ) frame_sent $end
$var reg 1 * is_busy $end
$var reg 1 + b_saved $end
$upscope $end
$enddefinitions $end
#0
1!
1"
b000000000000 #
1$
0%
0&
b000000000000 '
b0 (
0)
0*
0+
#4340000
0!
#8680000
1!
#13020000
0!
#17360000
1!
#21700000
0!
#26040000
1!
#30380000
0!
#34720000
1!
#39060000
0!
#42257000
#43400000
1!
b000110001001 #
#47740000
0!
#52080000
1!
1%
#56420000
0!
#60760000
1!
0%
#65100000
0!
#69440000
1!
#73780000
0!
#78120000
1!
#82460000
0!
#86800000
1!
#91140000
0!
#95480000
1!
#99820000
0!
#104160000
1!
#108500000
0!
#112840000
1!
#117180000
0!
#121520000
1!
#125860000
0!
#130200000
1!
#134540000
0!
#138880000
1!
#143220000
0!
#144944000
0"
#147560000
1!
#151900000
0!
#156240000
1!
#160580000
0!
#164920000
1!
#169260000
0!
#173600000
1!
#177940000
0!
#182280000
1!
#186620000
0!
#190960000
1!
#195300000
0!
#199640000
1!
#203980000
0!
#208320000
1!
#212660000
0!
#217000000
1!
#221340000
0!
#225680000
1!
#230020000
0!
#234360000
1!
#238700000
0!
#243040000
1!
#247380000
0!
#251720000
1!
#256060000
0!
#260400000
1!
#264740000
0!
#269080000
1!
#273420000
0!
#277760000
1!
#282100000
0!
#286440000
1!
#290780000
0!
#295120000
1!
#299460000
0!
#303800000
1!
#308140000
0!
#312480000
1!
#316820000
0!
#321160000
1!
#325500000
0!
#329840000
1!
#334180000
0!
#338520000
1!
#342860000
0!
#347200000
1!
#351540000
0!
#355880000
1!
#360220000
0!
#364560000
1!
#368900000
0!
#373240000
1!
#377580000
0!
#381920000
1!
#386260000
0!
#390600000
1!
#394940000
0!
#399280000
1!
1"
b000000000000 #
#403620000
0!
#407960000
1!
#412146000
#412300000
0!
#416640000
1!
b100110111111 #
#420980000
0!
#425320000
1!
1%
#429660000
0!
#434000000
1!
0%
#438340000
0!
#442680000
1!
#447020000
0!
#451360000
1!
#455700000
0!
#460040000
1!
#464380000
0!
#468720000
1!
#473060000
0!
#477400000
1!
#481740000
0!
#486080000
1!
#490420000
0!
#494760000
1!
#499100000
0!
#503440000
1!
#507780000
0!
#512120000
1!
#516460000
0!
#520800000
1!
#525140000
0!
#529480000
1!
#530555000
0"
