uart_tx/uart_tx.vhd
library ieee;
  use ieee.std_logic_1164.all;
  use ieee.numeric_std.all;

entity uart_tx is
    generic (
        DATA_BITS    : integer := 8;
        CLK_FREQ     : integer := 115200;  -- frequency of FPGA
        BAUD_RATE    : integer := 115200   -- Uart frequency
    );
    port (
        clk_i      : in  std_logic;
        rst_i      : in  std_logic;
        data_i     : in std_logic_vector((DATA_BITS-1) downto 0);
        tx_o       : out  std_logic;
        tx_order_i : in std_logic;
        tx_busy_o  : out std_logic
    );
end entity uart_tx;

architecture rtl_uart_tx of uart_tx is

     -- latch to save data_i while doing UART transactions
    signal b : std_logic_vector((DATA_BITS-1) downto 0);

    -- CLK_FREQ / BAUD_RATE = Clk hits per bit being sent
    constant CLKS_PER_BIT : integer := CLK_FREQ / BAUD_RATE; -- 1 hit / bit

    signal clk_count : integer range 0 to CLKS_PER_BIT - 1;
    signal bit_count : integer range 0 to DATA_BITS+2;

    --flags
    signal frame_sent : std_logic; --flag to know if dataframe has been sent before tx_order reset
    signal is_busy : std_logic;    -- flag to know if component is busy
    signal b_saved : std_logic;    --flag to know if data has been saved in latch
begin

tx_busy_o <= is_busy;
process(clk_i, rst_i)
begin
    if rst_i = '1' then --reset system
        tx_o <= '1';
        is_busy <= '0';
        --internal signals
        b <= (others => '0');
        b_saved <= '0';
        clk_count <= 0 ;
        bit_count <= 0;
        frame_sent <= '0';

        
    elsif rising_edge(clk_i) then
        -- FRAME State : Nothing to send, nothing is being sent
            if (tx_order_i = '0') and (frame_sent = '0') and (is_busy = '0') then
                --Reset for next UART Tx
                b <= (others => '0');
                b_saved <= '0';
                clk_count <= 0 ;
                bit_count <= 0;
        -- FRAME State : Frame isn't being sent/already sent, received order
            elsif (tx_order_i = '1') and (frame_sent = '0') and (is_busy = '0') then
                if b_saved = '0' then
                    b <= data_i; --saving data in a latch for safety as anything can happen to data_i
                    b_saved <= '1';
                    is_busy <= '1'; --starting Tx
                end if ;

        -- FRAME State : Frame is being sent
            elsif (is_busy = '1') and (frame_sent = '0') then
                -- Sending i-th bit
                if clk_count < CLKS_PER_BIT -1 then -- CLKS_PER_BIT = 1
                    clk_count <= clk_count + 1;

                else 
                    if bit_count = 0 then   
                        tx_o <= '0'; --START bit
                        bit_count <= bit_count +1;
                    
                    elsif bit_count < DATA_BITS + 1 then --"START + DATA" = DATA_BITS + 1 
                        tx_o <= b(bit_count-1);
                        bit_count <= bit_count + 1;
                        

                    elsif bit_count < DATA_BITS + 2 then --"START + DATA + STOP" = DATA_BITS + 2
                        tx_o <= '1'; --STOP bit
                        bit_count <= bit_count + 1;
                    else
                        frame_sent <= '1';

                    end if;
                clk_count <= 0; --reset for next bit

                end if;
        -- FRAME State : Already sent, waiting for tx_order_i reset
        -- for safety do not release busy flag here
            elsif (tx_order_i = '1') and (frame_sent = '1') and (is_busy = '1') then
                --Reset for next UART Tx
                b <= (others => '0');
                b_saved <= '0';
                clk_count <= 0 ;
                bit_count <= 0;

        -- FRAME State : Already sent, tx_order_i was resetted 
        -- => can reset frame_sent safely and release busy flag
            elsif (tx_order_i = '0') and (frame_sent = '1') and (is_busy = '1') then
                frame_sent <= '0';
                is_busy <= '0';
                --Reset for next UART Tx
                b <= (others => '0');
                b_saved <= '0';
                clk_count <= 0 ;
                bit_count <= 0;
            end if;

    end if;

end process;

end architecture rtl_uart_tx;

uart_tx/simulation_test_uart_tx.vcd
$date
  Sat Apr 18 22:00:09 2026
$end
$version
  GHDL v0
$end
$timescale
  1 ps
$end
$scope module standard $end
$upscope $end
$scope module std_logic_1164 $end
$upscope $end
$scope module numeric_std $end
$upscope $end
$scope module uart_tx $end
$var reg 1 ! clk_i $end
$var reg 1 " rst_i $end
$var reg 12 # data_i[11:0] $end
$var reg 1 $ tx_o $end
$var reg 1 % tx_order_i $end
$var reg 1 & tx_busy_o $end
$var reg 12 ' b[11:0] $end
$var integer 32 ( bit_count $end
$var reg 1 ) frame_sent $end
$var reg 1 * is_busy $end
$var reg 1 + b_saved $end
$upscope $end
$enddefinitions $end
#0
1!
1"
b000000000000 #
1$
0%
0&
b000000000000 '
b0 (
0)
0*
0+
#500
0!
#1000
1!
0"
b101101100101 #
#1500
0!
#2000
1!
1%
#2500
0!
#3000
1!
0%
1&
b101101100101 '
1*
1+
#3500
0!
#4000
1!
0$
b1 (
#4500
0!
#5000
1!
1$
b10 (
#5500
0!
#6000
1!
0$
b11 (
#6500
0!
#7000
1!
1$
b100 (
#7500
0!
#8000
1!
0$
b101 (
#8500
0!
#9000
1!
b110 (
#9500
0!
#10000
1!
1$
b111 (
#10500
0!
#11000
1!
b1000 (
#11500
0!
#12000
1!
0$
b1001 (
#12500
0!
#13000
1!
1$
b1010 (
#13500
0!
#14000
1!
b1011 (
#14500
0!
#15000
1!
0$
b1100 (
#15500
0!
#16000
1!
1$
b1101 (
#16500
0!
#17000
1!
b1110 (
#17500
0!
#18000
1!
1)
#18500
0!
#19000
1!
0&
b000000000000 '
b0 (
0)
0*
0+
#19500
0!
#20000
1!
#20500
0!
#21000
1!
#21500
0!
#22000
1!
#22500
0!
#23000
1!
#23500
0!
#24000
1!
b000110110101 #
#24500
0!
#25000
1!
1%
#25500
0!
#26000
1!
0%
1&
b000110110101 '
1*
1+
#26500
0!
#27000
1!
0$
b1 (
#27500
0!
#28000
1!
1$
b10 (
#28500
0!
#29000
1!
0$
b11 (
#29500
0!
#30000
1!
1$
b100 (
#30500
0!
#31000
1!
0$
b101 (
#31500
0!
#32000
1!
1$
b110 (
#32500
0!
#33000
1!
b111 (
#33500
0!
#34000
1!
0$
b1000 (
#34500
0!
#35000
1!
1$
b1001 (
#35500
0!
#36000
1!
b1010 (
#36500
0!
#37000
1!
0$
b1011 (
#37500
0!
#38000
1!
b1100 (
#38500
0!
#39000
1!
b1101 (
#39500
0!
#40000
1!
1$
b1110 (
#40500
0!
#41000
1!
1)
#41500
0!
#42000
1!
0&
b000000000000 '
b0 (
0)
0*
0+
#42500
0!
#43000
1!
#43500
0!
#44000
1!
#44500
0!
#45000
1!
#45500
0!
#46000
1!
#46500
0!
#47000
1!
b100000101001 #
#47500
0!
#48000
1!
1%
#48500
0!
#49000
1!
0%
1&
b100000101001 '
1*
1+
#49500
0!
#50000
1!
0$
b1 (
#50500
0!
#51000
1!
1$
b10 (
#51500
0!
#52000
1!
0$
b11 (
#52500
0!
#53000
1!
b100 (
#53500
0!
#54000
1!
1$
b101 (
#54500
0!
#55000
1!
0$
b110 (
#55500
0!
#56000
1!
1$
b111 (
#56500
0!
#57000
1!
0$
b1000 (
#57500
0!
#58000
1!
b1001 (
#58500
0!
#59000
1!
b1010 (
#59500
0!
#60000
1!
b1011 (
#60500
0!
#61000
1!
b1100 (
#61500
0!
#62000
1!
1$
b1101 (
#62500
0!
#63000
1!
b1110 (
#63500
0!
#64000
1!
1)
#64500
0!
#65000
1!
0&
b000000000000 '
b0 (
0)
0*
0+
#65500
0!
#66000
1!
#66500
0!
#67000
1!
#67500
0!
#68000
1!
#68500
0!
#69000
1!
#69500
0!
#70000
1!
b001001011100 #
#70500
0!
#71000
1!
1%
#71500
0!
#72000
1!
0%
1&
b001001011100 '
1*
1+
#72500
0!
#73000
1!
0$
b1 (
#73500
0!
#74000
1!
b10 (
#74500
0!
#75000
1!
b11 (
#75500
0!
#76000
1!
1$
b100 (
#76500
0!
#77000
1!
b101 (
#77500
0!
#78000
1!
b110 (
#78500
0!
#79000
1!
0$
b111 (
#79500
0!
#80000
1!
1$
b1000 (
#80500
0!
#81000
1!
0$
b1001 (
#81500
0!
#82000
1!
b1010 (
#82500
0!
#83000
1!
1$
b1011 (
#83500
0!
#84000
1!
0$
b1100 (
#84500
0!
#85000
1!
b1101 (
#85500
0!
#86000
1!
1$
b1110 (
#86500
0!
#87000
1!
1)
#87500
0!
#88000
1!
0&
b000000000000 '
b0 (
0)
0*
0+
#88500
0!
#89000
1!
#89500
0!
#90000
1!
#90500
0!
#91000
1!
#91500
0!
#92000
1!
#92500
0!
#93000
1!
b100110101101 #
#93500
0!
#94000
1!
1%
#94500
0!
#95000
1!
0%
1&
b100110101101 '
1*
1+
#95500
0!
#96000
1!
0$
b1 (
#96500
0!
#97000
1!
1$
b10 (
#97500
0!
#98000
1!
0$
b11 (
#98500
0!
#99000
1!
1$
b100 (
#99500
0!
#100000
1!
b101 (
#100500
0!
#101000
1!
0$
b110 (
#101500
0!
#102000
1!
1$
b111 (
#102500
0!
#103000
1!
0$
b1000 (
#103500
0!
#104000
1!
1$
b1001 (
#104500
0!
#105000
1!
b1010 (
#105500
0!
#106000
1!
0$
b1011 (
#106500
0!
#107000
1!
b1100 (
#107500
0!
#108000
1!
1$
b1101 (
#108500
0!
#109000
1!
b1110 (
#109500
0!
#110000
1!
1)
#110500
0!
#111000
1!
0&
b000000000000 '
b0 (
0)
0*
0+
#111500
0!
#112000
1!
#112500
0!
#113000
1!
#113500
0!
#114000
1!
#114500
0!
#115000
1!
#115500
0!
#116000
1!
b000101010110 #
#116500
0!
#117000
1!
1%
#117500
0!
#118000
1!
0%
1&
b000101010110 '
1*
1+
#118500
0!
#119000
1!
0$
b1 (
#119500
0!
#120000
1!
b10 (
#120500
0!
#121000
1!
1$
b11 (
#121500
0!
#122000
1!
b100 (
#122500
0!
#123000
1!
0$
b101 (
#123500
0!
#124000
1!
1$
b110 (
#124500
0!
#125000
1!
0$
b111 (
#125500
0!
#126000
1!
1$
b1000 (
#126500
0!
#127000
1!
0$
b1001 (
#127500
0!
#128000
1!
1$
b1010 (
#128500
0!
#129000
1!
0$
b1011 (
#129500
0!
#130000
1!
b1100 (
#130500
0!
#131000
1!
b1101 (
#131500
0!
#132000
1!
1$
b1110 (
#132500
0!
#133000
1!
1)
#133500
0!
#134000
1!
0&
b000000000000 '
b0 (
0)
0*
0+
#134500
0!
#135000
1!
#135500
0!
#136000
1!
#136500
0!
#137000
1!
#137500
0!
#138000
1!
#138500
0!
#139000
1!
b011010011100 #
#139500
0!
#140000
1!
1%
#140500
0!
#141000
1!
0%
1&
b011010011100 '
1*
1+
#141500
0!
#142000
1!
0$
b1 (
#142500
0!
#143000
1!
b10 (
#143500
0!
#144000
1!
b11 (
#144500
0!
#145000
1!
1$
b100 (
#145500
0!
#146000
1!
b101 (
#146500
0!
#147000
1!
b110 (
#147500
0!
#148000
1!
0$
b111 (
#148500
0!
#149000
1!
b1000 (
#149500
0!
#150000
1!
1$
b1001 (
#150500
0!
#151000
1!
0$
b1010 (
#151500
0!
#152000
1!
1$
b1011 (
#152500
0!
#153000
1!
b1100 (
#153500
0!
#154000
1!
0$
b1101 (
#154500
0!
#155000
1!
1$
b1110 (
#155500
0!
#156000
1!
1)
#156500
0!
#157000
1!
0&
b000000000000 '
b0 (
0)
0*
0+
#157500
0!
#158000
1!
#158500
0!
#159000
1!
#159500
0!
#160000
1!
#160500
0!
#161000
1!
#161500
0!
#162000
1!
b110110101000 #
#162500
0!
#163000
1!
1%
#163500
0!
#164000
1!
0%
1&
b110110101000 '
1*
1+
#164500
0!
#165000
1!
0$
b1 (
#165500
0!
#166000
1!
b10 (
#166500
0!
#167000
1!
b11 (
#167500
0!
#168000
1!
b100 (
#168500
0!
#169000
1!
1$
b101 (
#169500
0!
#170000
1!
0$
b110 (
#170500
0!
#171000
1!
1$
b111 (
#171500
0!
#172000
1!
0$
b1000 (
#172500
0!
#173000
1!
1$
b1001 (
#173500
0!
#174000
1!
b1010 (
#174500
0!
#175000
1!
0$
b1011 (
#175500
0!
#176000
1!
1$
b1100 (
#176500
0!
#177000
1!
b1101 (
#177500
0!
#178000
1!
b1110 (
#178500
0!
#179000
1!
1)
#179500
0!
#180000
1!
0&
b000000000000 '
b0 (
0)
0*
0+
#180500
0!
#181000
1!
#181500
0!
#182000
1!
#182500
0!
#183000
1!
#183500
0!
#184000
1!
#184500
0!
#185000
1!
b111001100101 #
#185500
0!
#186000
1!
1%
#186500
0!
#187000
1!
0%
1&
b111001100101 '
1*
1+
#187500
0!
#188000
1!
0$
b1 (
#188500
0!
#189000
1!
1$
b10 (
#189500
0!
#190000
1!
0$
b11 (
#190500
0!
#191000
1!
1$
b100 (
#191500
0!
#192000
1!
0$
b101 (
#192500
0!
#193000
1!
b110 (
#193500
0!
#194000
1!
1$
b111 (
#194500
0!
#195000
1!
b1000 (
#195500
0!
#196000
1!
0$
b1001 (
#196500
0!
#197000
1!
b1010 (
#197500
0!
#198000
1!
1$
b1011 (
#198500
0!
#199000
1!
b1100 (
#199500
0!
#200000
1!
b1101 (
#200500
0!
#201000
1!
b1110 (
#201500
0!
#202000
1!
1)
#202500
0!
#203000
1!
0&
b000000000000 '
b0 (
0)
0*
0+
#203500
0!
#204000
1!
#204500
0!
#205000
1!
#205500
0!
#206000
1!
#206500
0!
#207000
1!
#207500
0!
#208000
1!
b101101011011 #
#208500
0!
#209000
1!
1%
#209500
0!
#210000
1!
0%
1&
b101101011011 '
1*
1+
#210500
0!
#211000
1!
0$
b1 (
#211500
0!
#212000
1!
1$
b10 (
#212500
0!
#213000
1!
b11 (
#213500
0!
#214000
1!
0$
b100 (
#214500
0!
#215000
1!
1$
b101 (
#215500
0!
#216000
1!
b110 (
#216500
0!
#217000
1!
0$
b111 (
#217500
0!
#218000
1!
1$
b1000 (
#218500
0!
#219000
1!
0$
b1001 (
#219500
0!
#220000
1!
1$
b1010 (
#220500
0!
#221000
1!
b1011 (
#221500
0!
#222000
1!
0$
b1100 (
#222500
0!
#223000
1!
1$
b1101 (
#223500
0!
#224000
1!
b1110 (
#224500
0!
#225000
1!
1)
#225500
0!
#226000
1!
0&
b000000000000 '
b0 (
0)
0*
0+
#226500
0!
#227000
1!
#227500
0!
#228000
1!
#228500
0!
#229000
1!
#229500
0!
#230000
1!
#230500
0!
#231000
1!
b111010000101 #
#231500
0!
#232000
1!
1%
#232500
0!
#233000
1!
0%
1&
b111010000101 '
1*
1+
#233500
0!
#234000
1!
0$
b1 (
#234500
0!
#235000
1!
1$
b10 (
#235500
0!
#236000
1!
0$
b11 (
#236500
0!
#237000
1!
1$
b100 (
#237500
0!
#238000
1!
0$
b101 (
#238500
0!
#239000
1!
b110 (
#239500
0!
#240000
1!
b111 (
#240500
0!
#241000
1!
b1000 (
#241500
0!
#242000
1!
1$
b1001 (
#242500
0!
#243000
1!
0$
b1010 (
#243500
0!
#244000
1!
1$
b1011 (
#244500
0!
#245000
1!
b1100 (
#245500
0!
#246000
1!
b1101 (
#246500
0!
#247000
1!
b1110 (
#247500
0!
#248000
1!
1)
#248500
0!
#249000
1!
0&
b000000000000 '
b0 (
0)
0*
0+
#249500
0!
#250000
1!
#250500
0!
#251000
1!
#251500
0!
#252000
1!
#252500
0!
#253000
1!
#253500
0!
#254000
1!
b110001011001 #
#254500
0!
#255000
1!
1%
#255500
0!
#256000
1!
0%
1&
b110001011001 '
1*
1+
#256500
0!
#257000
1!
0$
b1 (
#257500
0!
#258000
1!
1$
b10 (
#258500
0!
#259000
1!
0$
b11 (
#259500
0!
#260000
1!
b100 (
#260500
0!
#261000
1!
1$
b101 (
#261500
0!
#262000
1!
b110 (
#262500
0!
#263000
1!
0$
b111 (
#263500
0!
#264000
1!
1$
b1000 (
#264500
0!
#265000
1!
0$
b1001 (
#265500
0!
#266000
1!
b1010 (
#266500
0!
#267000
1!
b1011 (
#267500
0!
#268000
1!
1$
b1100 (
#268500
0!
#269000
1!
b1101 (
#269500
0!
#270000
1!
b1110 (
#270500
0!
#271000
1!
1)
#271500
0!
#272000
1!
0&
b000000000000 '
b0 (
0)
0*
0+
#272500
0!
#273000
1!
#273500
0!
#274000
1!
#274500
0!
#275000
1!
#275500
0!
#276000
1!
#276500
0!
#277000
1!
b100111101100 #
#277500
0!
#278000
1!
1%
#278500
0!
#279000
1!
0%
1&
b100111101100 '
1*
1+
#279500
0!
#280000
1!
0$
b1 (
#280500
0!
#281000
1!
b10 (
#281500
0!
#282000
1!
b11 (
#282500
0!
#283000
1!
1$
b100 (
#283500
0!
#284000
1!
b101 (
#284500
0!
#285000
1!
0$
b110 (
#285500
0!
#286000
1!
1$
b111 (
#286500
0!
#287000
1!
b1000 (
#287500
0!
#288000
1!
b1001 (
#288500
0!
#289000
1!
b1010 (
#289500
0!
#290000
1!
0$
b1011 (
#290500
0!
#291000
1!
b1100 (
#291500
0!
#292000
1!
1$
b1101 (
#292500
0!
#293000
1!
b1110 (
#293500
0!
#294000
1!
1)
#294500
0!
#295000
1!
0&
b000000000000 '
b0 (
0)
0*
0+
#295500
0!
#296000
1!
#296500
0!
#297000
1!
#297500
0!
#298000
1!
#298500
0!
#299000
1!
#299500
0!
#300000
1!
b011000101111 #
#300500
0!
#301000
1!
1%
#301500
0!
#302000
1!
0%
1&
b011000101111 '
1*
1+
#302500
0!
#303000
1!
0$
b1 (
#303500
0!
#304000
1!
1$
b10 (
#304500
0!
#305000
1!
b11 (
#305500
0!
#306000
1!
b100 (
#306500
0!
#307000
1!
b101 (
#307500
0!
#308000
1!
0$
b110 (
#308500
0!
#309000
1!
1$
b111 (
#309500
0!
#310000
1!
0$
b1000 (
#310500
0!
#311000
1!
b1001 (
#311500
0!
#312000
1!
b1010 (
#312500
0!
#313000
1!
1$
b1011 (
#313500
0!
#314000
1!
b1100 (
#314500
0!
#315000
1!
0$
b1101 (
#315500
0!
#316000
1!
1$
b1110 (
#316500
0!
#317000
1!
1)
#317500
0!
#318000
1!
0&
b000000000000 '
b0 (
0)
0*
0+
#318500
0!
#319000
1!
#319500
0!
#320000
1!
#320500
0!
#321000
1!
#321500
0!
#322000
1!
#322500
0!
#323000
1!
b010000110011 #
#323500
0!
#324000
1!
1%
#324500
0!
#325000
1!
0%
1&
b010000110011 '
1*
1+
#325500
0!
#326000
1!
0$
b1 (
#326500
0!
#327000
1!
1$
b10 (
#327500
0!
#328000
1!
b11 (
#328500
0!
#329000
1!
0$
b100 (
#329500
0!
#330000
1!
b101 (
#330500
0!
#331000
1!
1$
b110 (
#331500
0!
#332000
1!
b111 (
#332500
0!
#333000
1!
0$
b1000 (
#333500
0!
#334000
1!
b1001 (
#334500
0!
#335000
1!
b1010 (
#335500
0!
#336000
1!
b1011 (
#336500
0!
#337000
1!
1$
b1100 (
#337500
0!
#338000
1!
0$
b1101 (
#338500
0!
#339000
1!
1$
b1110 (
#339500
0!
#340000
1!
1)
#340500
0!
#341000
1!
0&
b000000000000 '
b0 (
0)
0*
0+
#341500
0!
#342000
1!
#342500
0!
#343000
1!
#343500
0!
#344000
1!
#344500
0!
#345000
1!
#345500
0!
#346000
1!
b111111000111 #
#346500
0!
#347000
1!
1%
#347500
0!
#348000
1!
0%
1&
b111111000111 '
1*
1+
#348500
0!
#349000
1!
0$
b1 (
#349500
0!
#350000
1!
1$
b10 (
#350500
0!
#351000
1!
b11 (
#351500
0!
#352000
1!
b100 (
#352500
0!
#353000
1!
0$
b101 (
#353500
0!
#354000
1!
b110 (
#354500
0!
#355000
1!
b111 (
#355500
0!
#356000
1!
1$
b1000 (
#356500
0!
#357000
1!
b1001 (
#357500
0!
#358000
1!
b1010 (
#358500
0!
#359000
1!
b1011 (
#359500
0!
#360000
1!
b1100 (
#360500
0!
#361000
1!
b1101 (
#361500
0!
#362000
1!
b1110 (
#362500
0!
#363000
1!
1)
#363500
0!
#364000
1!
0&
b000000000000 '
b0 (
0)
0*
0+
#364500
0!
#365000
1!
#365500
0!
#366000
1!
#366500
0!
#367000
1!
#367500
0!
#368000
1!
#368500
0!
#369000
1!
b101100001001 #
#369500
0!
#370000
1!
1%
#370500
0!
#371000
1!
0%
1&
b101100001001 '
1*
1+
#371500
0!
#372000
1!
0$
b1 (
#372500
0!
#373000
1!
1$
b10 (
#373500
0!
#374000
1!
0$
b11 (
#374500
0!
#375000
1!
b100 (
#375500
0!
#376000
1!
1$
b101 (
#376500
0!
#377000
1!
0$
b110 (
#377500
0!
#378000
1!
b111 (
#378500
0!
#379000
1!
b1000 (
#379500
0!
#380000
1!
b1001 (
#380500
0!
#381000
1!
1$
b1010 (
#381500
0!
#382000
1!
b1011 (
#382500
0!
#383000
1!
0$
b1100 (
#383500
0!
#384000
1!
1$
b1101 (
#384500
0!
#385000
1!
b1110 (
#385500
0!
#386000
1!
1)
#386500
0!
#387000
1!
0&
b000000000000 '
b0 (
0)
0*
0+
#387500
0!
#388000
1!
#388500
0!
#389000
1!
#389500
0!
#390000
1!
#390500
0!
#391000
1!
#391500
0!
#392000
1!
b010100100111 #
#392500
0!
#393000
1!
1%
#393500
0!
#394000
1!
0%
1&
b010100100111 '
1*
1+
#394500
0!
#395000
1!
0$
b1 (
#395500
0!
#396000
1!
1$
b10 (
#396500
0!
#397000
1!
b11 (
#397500
0!
#398000
1!
b100 (
#398500
0!
#399000
1!
0$
b101 (
#399500
0!
#400000
1!
b110 (
#400500
0!
#401000
1!
1$
b111 (
#401500
0!
#402000
1!
0$
b1000 (
#402500
0!
#403000
1!
b1001 (
#403500
0!
#404000
1!
1$
b1010 (
#404500
0!
#405000
1!
0$
b1011 (
#405500
0!
#406000
1!
1$
b1100 (
#406500
0!
#407000
1!
0$
b1101 (
#407500
0!
#408000
1!
1$
b1110 (
#408500
0!
#409000
1!
1)
#409500
0!
#410000
1!
0&
b000000000000 '
b0 (
0)
0*
0+
#410500
0!
#411000
1!
#411500
0!
#412000
1!
#412500
0!
#413000
1!
#413500
0!
#414000
1!
#414500
0!
#415000
1!
b000111110010 #
#415500
0!
#416000
1!
1%
#416500
0!
#417000
1!
0%
1&
b000111110010 '
1*
1+
#417500
0!
#418000
1!
0$
b1 (
#418500
0!
#419000
1!
b10 (
#419500
0!
#420000
1!
1$
b11 (
#420500
0!
#421000
1!
0$
b100 (
#421500
0!
#422000
1!
b101 (
#422500
0!
#423000
1!
1$
b110 (
#423500
0!
#424000
1!
b111 (
#424500
0!
#425000
1!
b1000 (
#425500
0!
#426000
1!
b1001 (
#426500
0!
#427000
1!
b1010 (
#427500
0!
#428000
1!
0$
b1011 (
#428500
0!
#429000
1!
b1100 (
#429500
0!
#430000
1!
b1101 (
#430500
0!
#431000
1!
1$
b1110 (
#431500
0!
#432000
1!
1)
#432500
0!
#433000
1!
0&
b000000000000 '
b0 (
0)
0*
0+
#433500
0!
#434000
1!
#434500
0!
#435000
1!
#435500
0!
#436000
1!
#436500
0!
#437000
1!
#437500
0!
#438000
1!
b010101010010 #
#438500
0!
#439000
1!
1%
#439500
0!
#440000
1!
0%
1&
b010101010010 '
1*
1+
#440500
0!
#441000
1!
0$
b1 (
#441500
0!
#442000
1!
b10 (
#442500
0!
#443000
1!
1$
b11 (
#443500
0!
#444000
1!
0$
b100 (
#444500
0!
#445000
1!
b101 (
#445500
0!
#446000
1!
1$
b110 (
#446500
0!
#447000
1!
0$
b111 (
#447500
0!
#448000
1!
1$
b1000 (
#448500
0!
#449000
1!
0$
b1001 (
#449500
0!
#450000
1!
1$
b1010 (
#450500
0!
#451000
1!
0$
b1011 (
#451500
0!
#452000
1!
1$
b1100 (
#452500
0!
#453000
1!
0$
b1101 (
#453500
0!
#454000
1!
1$
b1110 (
#454500
0!
#455000
1!
1)
#455500
0!
#456000
1!
0&
b000000000000 '
b0 (
0)
0*
0+
#456500
0!
#457000
1!
#457500
0!
#458000
1!
#458500
0!
#459000
1!
#459500
0!
#460000
1!
#460500
0!
#461000
1!
b011101000100 #
#461500
0!
#462000
1!
1%
#462500
0!
#463000
1!
0%
1&
b011101000100 '
1*
1+
#463500
0!
#464000
1!
0$
b1 (
#464500
0!
#465000
1!
b10 (
#465500
0!
#466000
1!
b11 (
#466500
0!
#467000
1!
1$
b100 (
#467500
0!
#468000
1!
0$
b101 (
#468500
0!
#469000
1!
b110 (
#469500
0!
#470000
1!
b111 (
#470500
0!
#471000
1!
1$
b1000 (
#471500
0!
#472000
1!
0$
b1001 (
#472500
0!
#473000
1!
1$
b1010 (
#473500
0!
#474000
1!
b1011 (
#474500
0!
#475000
1!
b1100 (
#475500
0!
#476000
1!
0$
b1101 (
#476500
0!
#477000
1!
1$
b1110 (
#477500
0!
#478000
1!
1)
#478500
0!
#479000
1!
0&
b000000000000 '
b0 (
0)
0*
0+
#479500
0!
#480000
1!
#480500
0!
#481000
1!
#481500
0!
#482000
1!
#482500
0!
#483000
1!
#483500
0!
#484000
1!
b011111101011 #
#484500
0!
#485000
1!
1%
#485500
0!
#486000
1!
0%
1&
b011111101011 '
1*
1+
#486500
0!
#487000
1!
0$
b1 (
#487500
0!
#488000
1!
1$
b10 (
#488500
0!
#489000
1!
b11 (
#489500
0!
#490000
1!
0$
b100 (
#490500
0!
#491000
1!
1$
b101 (
#491500
0!
#492000
1!
0$
b110 (
#492500
0!
#493000
1!
1$
b111 (
#493500
0!
#494000
1!
b1000 (
#494500
0!
#495000
1!
b1001 (
#495500
0!
#496000
1!
b1010 (
#496500
0!
#497000
1!
b1011 (
#497500
0!
#498000
1!
b1100 (
#498500
0!
#499000
1!
0$
b1101 (
#499500
0!
#500000
1!
1$
b1110 (
#500500
0!
#501000
1!
1)
#501500
0!
#502000
1!
0&
b000000000000 '
b0 (
0)
0*
0+
#502500
0!
#503000
1!
#503500
0!
#504000
1!
#504500
0!
#505000
1!
#505500
0!
#506000
1!
#506500
0!
#507000
1!
b001000100011 #
#507500
0!
#508000
1!
1%
#508500
0!
#509000
1!
0%
1&
b001000100011 '
1*
1+
#509500
0!
#510000
1!
0$
b1 (
#510500
0!
#511000
1!
1$
b10 (
#511500
0!
#512000
1!
b11 (
#512500
0!
#513000
1!
0$
b100 (
#513500
0!
#514000
1!
b101 (
#514500
0!
#515000
1!
b110 (
#515500
0!
#516000
1!
1$
b111 (
#516500
0!
#517000
1!
0$
b1000 (
#517500
0!
#518000
1!
b1001 (
#518500
0!
#519000
1!
b1010 (
#519500
0!
#520000
1!
1$
b1011 (
#520500
0!
#521000
1!
0$
b1100 (
#521500
0!
#522000
1!
b1101 (
#522500
0!
#523000
1!
1$
b1110 (
#523500
0!
#524000
1!
1)
#524500
0!
#525000
1!
0&
b000000000000 '
b0 (
0)
0*
0+
#525500
0!
#526000
1!
#526500
0!
#527000
1!
#527500
0!
#528000
1!
#528500
0!
#529000
1!
#529500
0!
#530000
1!
b010001000010 #
#530500
0!
#531000
1!
1%
#531500
0!
#532000
1!
0%
1&
b010001000010 '
1*
1+
#532500
0!
#533000
1!
0$
b1 (
#533500
0!
#534000
1!
b10 (
#534500
0!
#535000
1!
1$
b11 (
#535500
0!
#536000
1!
0$
b100 (
#536500
0!
#537000
1!
b101 (
#537500
0!
#538000
1!
b110 (
#538500
0!
#539000
1!
b111 (
#539500
0!
#540000
1!
1$
b1000 (
#540500
0!
#541000
1!
0$
b1001 (
#541500
0!
#542000
1!
b1010 (
#542500
0!
#543000
1!
b1011 (
#543500
0!
#544000
1!
1$
b1100 (
#544500
0!
#545000
1!
0$
b1101 (
#545500
0!
#546000
1!
1$
b1110 (
#546500
0!
#547000
1!
1)
#547500
0!
#548000
1!
0&
b000000000000 '
b0 (
0)
0*
0+
#548500
0!
#549000
1!
#549500
0!
#550000
1!
#550500
0!
#551000
1!
#551500
0!
#552000
1!
#552500
0!
#553000
1!
b110000011101 #
#553500
0!
#554000
1!
1%
#554500
0!
#555000
1!
0%
1&
b110000011101 '
1*
1+
#555500
0!
#556000
1!
0$
b1 (
#556500
0!
#557000
1!
1$
b10 (
#557500
0!
#558000
1!
0$
b11 (
#558500
0!
#559000
1!
1$
b100 (
#559500
0!
#560000
1!
b101 (
#560500
0!
#561000
1!
b110 (
#561500
0!
#562000
1!
0$
b111 (
#562500
0!
#563000
1!
b1000 (
#563500
0!
#564000
1!
b1001 (
#564500
0!
#565000
1!
b1010 (
#565500
0!
#566000
1!
b1011 (
#566500
0!
#567000
1!
1$
b1100 (
#567500
0!
#568000
1!
b1101 (
#568500
0!
#569000
1!
b1110 (
#569500
0!
#570000
1!
1)
#570500
0!
#571000
1!
0&
b000000000000 '
b0 (
0)
0*
0+
#571500
0!
#572000
1!
#572500
0!
#573000
1!
#573500
0!
#574000
1!
#574500
0!
#575000
1!
#575500
0!
#576000
1!
b011101110010 #
#576500
0!
#577000
1!
1%
#577500
0!
#578000
1!
0%
1&
b011101110010 '
1*
1+
#578500
0!
#579000
1!
0$
b1 (
#579500
0!
#580000
1!
b10 (
#580500
0!
#581000
1!
1$
b11 (
#581500
0!
#582000
1!
0$
b100 (
#582500
0!
#583000
1!
b101 (
#583500
0!
#584000
1!
1$
b110 (
#584500
0!
#585000
1!
b111 (
#585500
0!
#586000
1!
b1000 (
#586500
0!
#587000
1!
0$
b1001 (
#587500
0!
#588000
1!
1$
b1010 (
#588500
0!
#589000
1!
b1011 (
#589500
0!
#590000
1!
b1100 (
#590500
0!
#591000
1!
0$
b1101 (
#591500
0!
#592000
1!
1$
b1110 (
#592500
0!
#593000
1!
1)
#593500
0!
#594000
1!
0&
b000000000000 '
b0 (
0)
0*
0+
#594500
0!
#595000
1!
#595500
0!
#596000
1!
#596500
0!
#597000
1!
#597500
0!
#598000
1!
#598500
0!
#599000
1!
b001110001000 #
#599500
0!
#600000
1!
1%
#600500
0!
#601000
1!
0%
1&
b001110001000 '
1*
1+
#601500
0!
#602000
1!
0$
b1 (
#602500
0!
#603000
1!
b10 (
#603500
0!
#604000
1!
b11 (
#604500
0!
#605000
1!
b100 (
#605500
0!
#606000
1!
1$
b101 (
#606500
0!
#607000
1!
0$
b110 (
#607500
0!
#608000
1!
b111 (
#608500
0!
#609000
1!
b1000 (
#609500
0!
#610000
1!
1$
b1001 (
#610500
0!
#611000
1!
b1010 (
#611500
0!
#612000
1!
b1011 (
#612500
0!
#613000
1!
0$
b1100 (
#613500
0!
#614000
1!
b1101 (
#614500
0!
