uart_rx/uart_rx.vhd
library ieee;
  use ieee.std_logic_1164.all;
  use ieee.numeric_std.all;

entity uart_rx is
    generic (
        DATA_BITS    : integer := 12;
        CLK_FREQ     : integer := 50_000_000;  -- fréquence horloge système
        BAUD_RATE    : integer := 115200
    );
    port (
        clk_i  : in  std_logic;
        rst_i  : in  std_logic;
        rx_i   : in  std_logic;
        data_o : out std_logic_vector((DATA_BITS-1) downto 0);
        flag_rx_o : out std_logic
    );
end entity uart_rx;

architecture rtl_uart_rx of uart_rx is

    type uart_state_t is (IDLE, START, DATA, STOP);
    signal state     : uart_state_t;
    signal b : std_logic_vector((DATA_BITS-1) downto 0); -- bascule pour data

    -- Rapport CLK_FREQ / BAUD_RATE = nombre de coups d'horloge par bit
    constant CLKS_PER_BIT : integer := CLK_FREQ / BAUD_RATE; -- 434 coups d'horloges de Rx / bit reçu de Tx

    signal clk_count : integer range 0 to CLKS_PER_BIT - 1;
    signal data_bit_count : integer range 0 to DATA_BITS;

begin

process(clk_i, rst_i)
begin
    if rst_i = '1' then
        state <= IDLE;
    elsif rising_edge(clk_i) then
        case state is
            when IDLE =>
                if rx_i = '0' then
                    state <= START;
                    clk_count <= 0;
                    flag_rx_o <= '0';
                    data_o <= (others => '0');
                else 
                    state <= IDLE; --we keep the else to avoid synthetizer putting additional latch
                end if;
            when START => 
                if clk_count < CLKS_PER_BIT/2 then -- CLKS_PER_BIT/2 = 217
                    clk_count <= clk_count+1;
                    state <= START;
                else
                    clk_count <= 0; --prepare pour DATA
                    data_bit_count <= 0; --prepare pour DATA
                    state <=  DATA;
               end if;
            when DATA  => 
                if clk_count < CLKS_PER_BIT -1 then -- CLKS_PER_BIT = 434
                    clk_count <= clk_count + 1;
                    state <= DATA;
                else
                    if data_bit_count < DATA_BITS then
                        b(DATA_BITS-1) <= rx_i;
                        
                        for i in 0 to ((DATA_BITS-1) - 1) loop
                        b(DATA_BITS-1 - (i+1)) <= b(DATA_BITS-1 - i);
                        end loop;

                        data_bit_count <= data_bit_count + 1;
                        clk_count <= 0;
                    else
                        clk_count <= 0;
                        state <= STOP;
                    end if;
                end if;

            when STOP  =>
                if clk_count < CLKS_PER_BIT/2 then
                    clk_count <= clk_count+1;
                    state <= STOP;
                else 
                    if rx_i = '1' then -- comportement normal
                        data_o <= b;
                        flag_rx_o <= '1';
                    else --problème dans la trame : STOP non reçu
                        flag_rx_o <= '0'; -- flag : erreur
                    end if;
                    state <= IDLE;
                end if;
        end case;
    end if;
end process;

end architecture rtl_uart_rx;

uart_rx/simulation.vcd
$date
  Sat Apr 18 15:46:00 2026
$end
$version
  GHDL v0
$end
$timescale
  1 ps
$end
$scope module standard $end
$upscope $end
$scope module std_logic_1164 $end
$upscope $end
$scope module numeric_std $end
$upscope $end
$scope module uart_rx $end
$var reg 1 ! clk_i $end
$var reg 1 " rst_i $end
$var reg 1 # rx_i $end
$var reg 12 $ data_o[11:0] $end
$var reg 1 % flag_rx_o $end
$comment state is not handled $end
$var reg 12 & b[11:0] $end
$var integer 32 ' clk_count $end
$var integer 32 ( data_bit_count $end
$upscope $end
$enddefinitions $end
#0
1!
1"
1#
b000000000000 $
0%
b000000000000 &
b0 '
b0 (
#500
0!
#1000
1!
#1500
0!
#2000
1!
#2500
0!
#3000
1!
#3500
0!
#4000
1!
#4500
0!
#5000
1!
#5500
0!
#6000
1!
#6500
0!
#7000
1!
#7500
0!
#8000
1!
#8500
0!
#9000
1!
#9500
0!
#10000
1!
#10500
0!
#11000
1!
#11500
0!
#12000
1!
#12500
0!
#13000
1!
#13500
0!
#14000
1!
#14500
0!
#15000
1!
#15500
0!
#16000
1!
#16500
0!
#17000
1!
#17500
0!
#18000
1!
#18500
0!
#19000
1!
#19500
0!
#20000
1!
#20500
0!
#21000
1!
#21500
0!
#22000
1!
#22500
0!
#23000
1!
#23500
0!
#24000
1!
#24500
0!
#25000
1!
#25500
0!
#26000
1!
#26500
0!
#27000
1!
#27500
0!
#28000
1!
#28500
0!
#29000
1!
#29500
0!
#30000
1!
#30500
0!
#31000
1!
#31500
0!
#32000
1!
#32500
0!
#33000
1!
#33500
0!
#34000
1!
#34500
0!
#35000
1!
#35500
0!
#36000
1!
#36500
0!
#37000
1!
#37500
0!
#38000
1!
#38500
0!
#39000
1!
#39500
0!
#40000
1!
#40500
0!
#41000
1!
#41500
0!
#42000
1!
#42500
0!
#43000
1!
#43500
0!
#44000
1!
#44500
0!
#45000
1!
#45500
0!
#46000
1!
#46500
0!
#47000
1!
#47500
0!
#48000
1!
#48500
0!
#49000
1!
#49500
0!
#50000
1!
#50500
0!
#51000
1!
#51500
0!
#52000
1!
#52500
0!
#53000
1!
#53500
0!
#54000
1!
#54500
0!
#55000
1!
#55500
0!
#56000
1!
#56500
0!
#57000
1!
#57500
0!
#58000
1!
#58500
0!
#59000
1!
#59500
0!
#60000
1!
#60500
0!
#61000
1!
#61500
0!
#62000
1!
#62500
0!
#63000
1!
#63500
0!
#64000
1!
#64500
0!
#65000
1!
#65500
0!
#66000
1!
#66500
0!
#67000
1!
#67500
0!
#68000
1!
#68500
0!
#69000
1!
#69500
0!
#70000
1!
#70500
0!
#71000
1!
#71500
0!
#72000
1!
#72500
0!
#73000
1!
#73500
0!
#74000
1!
#74500
0!
#75000
1!
#75500
0!
#76000
1!
#76500
0!
#77000
1!
#77500
0!
#78000
1!
#78500
0!
#79000
1!
#79500
0!
#80000
1!
#80500
0!
#81000
1!
#81500
0!
#82000
1!
#82500
0!
#83000
1!
#83500
0!
#84000
1!
#84500
0!
#85000
1!
#85500
0!
#86000
1!
#86500
0!
#87000
1!
#87500
0!
#88000
1!
#88500
0!
#89000
1!
#89500
0!
#90000
1!
#90500
0!
#91000
1!
#91500
0!
#92000
1!
#92500
0!
#93000
1!
#93500
0!
#94000
1!
#94500
0!
#95000
1!
#95500
0!
#96000
1!
#96500
0!
#97000
1!
#97500
0!
#98000
1!
#98500
0!
#99000
1!
#99500
0!
#100000
1!
#100500
0!
#101000
1!
#101500
0!
#102000
1!
#102500
0!
#103000
1!
#103500
0!
#104000
1!
#104500
0!
#105000
1!
#105500
0!
#106000
1!
#106500
0!
#107000
1!
#107500
0!
#108000
1!
#108500
0!
#109000
1!
#109500
0!
#110000
1!
#110500
0!
#111000
1!
#111500
0!
#112000
1!
#112500
0!
#113000
1!
#113500
0!
#114000
1!
#114500
0!
#115000
1!
#115500
0!
#116000
1!
#116500
0!
#117000
1!
#117500
0!
#118000
1!
#118500
0!
#119000
1!
#119500
0!
#120000
1!
#120500
0!
#121000
1!
#121500
0!
#122000
1!
#122500
0!
#123000
1!
#123500
0!
#124000
1!
#124500
0!
#125000
1!
#125500
0!
#126000
1!
#126500
0!
#127000
1!
#127500
0!
#128000
1!
#128500
0!
#129000
1!
#129500
0!
#130000
1!
#130500
0!
#131000
1!
#131500
0!
#132000
1!
#132500
0!
#133000
1!
#133500
0!
#134000
1!
#134500
0!
#135000
1!
#135500
0!
#136000
1!
#136500
0!
#137000
1!
#137500
0!
#138000
1!
#138500
0!
#139000
1!
#139500
0!
#140000
1!
#140500
0!
#141000
1!
#141500
0!
#142000
1!
#142500
0!
#143000
1!
#143500
0!
#144000
1!
#144500
0!
#145000
1!
#145500
0!
#146000
1!
#146500
0!
#147000
1!
#147500
0!
#148000
1!
#148500
0!
#149000
1!
#149500
0!
#150000
1!
#150500
0!
#151000
1!
#151500
0!
#152000
1!
#152500
0!
#153000
1!
#153500
0!
#154000
1!
#154500
0!
#155000
1!
#155500
0!
#156000
1!
#156500
0!
#157000
1!
#157500
0!
#158000
1!
#158500
0!
#159000
1!
#159500
0!
#160000
1!
#160500
0!
#161000
1!
#161500
0!
#162000
1!
#162500
0!
#163000
1!
#163500
0!
#164000
1!
#164500
0!
#165000
1!
#165500
0!
#166000
1!
#166500
0!
#167000
1!
#167500
0!
#168000
1!
#168500
0!
#169000
1!
#169500
0!
#170000
1!
#170500
0!
#171000
1!
#171500
0!
#172000
1!
#172500
0!
#173000
1!
#173500
0!
#174000
1!
#174500
0!
#175000
1!
#175500
0!
#176000
1!
#176500
0!
#177000
1!
#177500
0!
#178000
1!
#178500
0!
#179000
1!
#179500
0!
#180000
1!
#180500
0!
#181000
1!
#181500
0!
#182000
1!
#182500
0!
#183000
1!
#183500
0!
#184000
1!
#184500
0!
#185000
1!
#185500
0!
#186000
1!
#186500
0!
#187000
1!
#187500
0!
#188000
1!
#188500
0!
#189000
1!
#189500
0!
#190000
1!
#190500
0!
#191000
1!
#191500
0!
#192000
1!
#192500
0!
#193000
1!
#193500
0!
#194000
1!
#194500
0!
#195000
1!
#195500
0!
#196000
1!
#196500
0!
#197000
1!
#197500
0!
#198000
1!
#198500
0!
#199000
1!
#199500
0!
#200000
1!
#200500
0!
#201000
1!
#201500
0!
#202000
1!
#202500
0!
#203000
1!
#203500
0!
#204000
1!
#204500
0!
#205000
1!
#205500
0!
#206000
1!
#206500
0!
#207000
1!
#207500
0!
#208000
1!
#208500
0!
#209000
1!
#209500
0!
#210000
1!
#210500
0!
#211000
1!
#211500
0!
#212000
1!
#212500
0!
#213000
1!
#213500
0!
#214000
1!
#214500
0!
#215000
1!
#215500
0!
#216000
1!
#216500
0!
#217000
1!
#217500
0!
#218000
1!
#218500
0!
#219000
1!
#219500
0!
#220000
1!
#220500
0!
#221000
1!
#221500
0!
#222000
1!
#222500
0!
#223000
1!
#223500
0!
#224000
1!
#224500
0!
#225000
1!
#225500
0!
#226000
1!
#226500
0!
#227000
1!
#227500
0!
#228000
1!
#228500
0!
#229000
1!
#229500
0!
#230000
1!
#230500
0!
#231000
1!
#231500
0!
#232000
1!
#232500
0!
#233000
1!
#233500
0!
#234000
1!
#234500
0!
#235000
1!
#235500
0!
#236000
1!
#236500
0!
#237000
1!
#237500
0!
#238000
1!
#238500
0!
#239000
1!
#239500
0!
#240000
1!
#240500
0!
#241000
1!
#241500
0!
#242000
1!
#242500
0!
#243000
1!
#243500
0!
#244000
1!
#244500
0!
#245000
1!
#245500
0!
#246000
1!
#246500
0!
#247000
1!
#247500
0!
#248000
1!
#248500
0!
#249000
1!
#249500
0!
#250000
1!
#250500
0!
#251000
1!
#251500
0!
#252000
1!
#252500
0!
#253000
1!
#253500
0!
#254000
1!
#254500
0!
#255000
1!
#255500
0!
#256000
1!
#256500
0!
#257000
1!
#257500
0!
#258000
1!
#258500
0!
#259000
1!
#259500
0!
#260000
1!
#260500
0!
#261000
1!
#261500
0!
#262000
1!
#262500
0!
#263000
1!
#263500
0!
#264000
1!
#264500
0!
#265000
1!
#265500
0!
#266000
1!
#266500
0!
#267000
1!
#267500
0!
#268000
1!
#268500
0!
#269000
1!
#269500
0!
#270000
1!
#270500
0!
#271000
1!
#271500
0!
#272000
1!
#272500
0!
#273000
1!
#273500
0!
#274000
1!
#274500
0!
#275000
1!
#275500
0!
#276000
1!
#276500
0!
#277000
1!
#277500
0!
#278000
1!
#278500
0!
#279000
1!
#279500
0!
#280000
1!
#280500
0!
#281000
1!
#281500
0!
#282000
1!
#282500
0!
#283000
1!
#283500
0!
#284000
1!
#284500
0!
#285000
1!
#285500
0!
#286000
1!
#286500
0!
#287000
1!
#287500
0!
#288000
1!
#288500
0!
#289000
1!
#289500
0!
#290000
1!
#290500
0!
#291000
1!
#291500
0!
#292000
1!
#292500
0!
#293000
1!
#293500
0!
#294000
1!
#294500
0!
#295000
1!
#295500
0!
#296000
1!
#296500
0!
#297000
1!
#297500
0!
#298000
1!
#298500
0!
#299000
1!
#299500
0!
#300000
1!
#300500
0!
#301000
1!
#301500
0!
#302000
1!
#302500
0!
#303000
1!
#303500
0!
#304000
1!
#304500
0!
#305000
1!
#305500
0!
#306000
1!
#306500
0!
#307000
1!
#307500
0!
#308000
1!
#308500
0!
#309000
1!
#309500
0!
#310000
1!
#310500
0!
#311000
1!
#311500
0!
#312000
1!
#312500
0!
#313000
1!
#313500
0!
#314000
1!
#314500
0!
#315000
1!
#315500
0!
#316000
1!
#316500
0!
#317000
1!
#317500
0!
#318000
1!
#318500
0!
#319000
1!
#319500
0!
#320000
1!
#320500
0!
#321000
1!
#321500
0!
#322000
1!
#322500
0!
#323000
1!
#323500
0!
#324000
1!
#324500
0!
#325000
1!
#325500
0!
#326000
1!
#326500
0!
#327000
1!
#327500
0!
#328000
1!
#328500
0!
#329000
1!
#329500
0!
#330000
1!
#330500
0!
#331000
1!
#331500
0!
#332000
1!
#332500
0!
#333000
1!
#333500
0!
#334000
1!
#334500
0!
#335000
1!
#335500
0!
#336000
1!
#336500
0!
#337000
1!
#337500
0!
#338000
1!
#338500
0!
#339000
1!
#339500
0!
#340000
1!
#340500
0!
#341000
1!
#341500
0!
#342000
1!
#342500
0!
#343000
1!
#343500
0!
#344000
1!
#344500
0!
#345000
1!
#345500
0!
#346000
1!
#346500
0!
#347000
1!
#347500
0!
#348000
1!
#348500
0!
#349000
1!
#349500
0!
#350000
1!
#350500
0!
#351000
1!
#351500
0!
#352000
1!
#352500
0!
#353000
1!
#353500
0!
#354000
1!
#354500
0!
#355000
1!
#355500
0!
#356000
1!
#356500
0!
#357000
1!
#357500
0!
#358000
1!
#358500
0!
#359000
1!
#359500
0!
#360000
1!
#360500
0!
#361000
1!
#361500
0!
#362000
1!
#362500
0!
#363000
1!
#363500
0!
#364000
1!
#364500
0!
#365000
1!
#365500
0!
#366000
1!
#366500
0!
#367000
1!
#367500
0!
#368000
1!
#368500
0!
#369000
1!
#369500
0!
#370000
1!
#370500
0!
#371000
1!
#371500
0!
#372000
1!
#372500
0!
#373000
1!
#373500
0!
#374000
1!
#374500
0!
#375000
1!
#375500
0!
#376000
1!
#376500
0!
#377000
1!
#377500
0!
#378000
1!
#378500
0!
#379000
1!
#379500
0!
#380000
1!
#380500
0!
#381000
1!
#381500
0!
#382000
1!
#382500
0!
#383000
1!
#383500
0!
#384000
1!
#384500
0!
#385000
1!
#385500
0!
#386000
1!
#386500
0!
#387000
1!
#387500
0!
#388000
1!
#388500
0!
#389000
1!
#389500
0!
#390000
1!
#390500
0!
#391000
1!
#391500
0!
#392000
1!
#392500
0!
#393000
1!
#393500
0!
#394000
1!
#394500
0!
#395000
1!
#395500
0!
#396000
1!
#396500
0!
#397000
1!
#397500
0!
#398000
1!
#398500
0!
#399000
1!
#399500
0!
#400000
1!
#400500
0!
#401000
1!
#401500
0!
#402000
1!
#402500
0!
#403000
1!
#403500
0!
#404000
1!
#404500
0!
#405000
1!
#405500
0!
#406000
1!
#406500
0!
#407000
1!
#407500
0!
#408000
1!
#408500
0!
#409000
1!
#409500
0!
#410000
1!
#410500
0!
#411000
1!
#411500
0!
#412000
1!
#412500
0!
#413000
1!
#413500
0!
#414000
1!
#414500
0!
#415000
1!
#415500
0!
#416000
1!
#416500
0!
#417000
1!
#417500
0!
#418000
1!
#418500
0!
#419000
1!
#419500
0!
#420000
1!
#420500
0!
#421000
1!
#421500
0!
#422000
1!
#422500
0!
#423000
1!
#423500
0!
#424000
1!
#424500
0!
#425000
1!
#425500
0!
#426000
1!
#426500
0!
#427000
1!
#427500
0!
#428000
1!
#428500
0!
#429000
1!
#429500
0!
#430000
1!
#430500
0!
#431000
1!
#431500
0!
#432000
1!
#432500
0!
#433000
1!
#433500
0!
#434000
1!
0"
#434500
0!
#435000
1!
#435500
0!
#436000
1!
#436500
0!
#437000
1!
#437500
0!
#438000
1!
#438500
0!
#439000
1!
#439500
0!
#440000
1!
#440500
0!
#441000
1!
#441500
0!
#442000
1!
#442500
0!
#443000
1!
#443500
0!
#444000
1!
0#
#444500
0!
#445000
1!
#445500
0!
#446000
1!
b1 '
#446500
0!
#447000
1!
b10 '
#447500
0!
#448000
1!
b11 '
#448500
0!
#449000
1!
b100 '
#449500
0!
#450000
1!
b101 '
#450500
0!
#451000
1!
b110 '
#451500
0!
#452000
1!
b111 '
#452500
0!
#453000
1!
b1000 '
#453500
0!
#454000
1!
b1001 '
#454500
0!
#455000
1!
b1010 '
#455500
0!
#456000
1!
b1011 '
#456500
0!
#457000
1!
b1100 '
#457500
0!
#458000
1!
b1101 '
#458500
0!
#459000
1!
b1110 '
#459500
0!
#460000
1!
b1111 '
#460500
0!
#461000
1!
b10000 '
#461500
0!
#462000
1!
b10001 '
#462500
0!
#463000
1!
b10010 '
#463500
0!
#464000
1!
b10011 '
#464500
0!
#465000
1!
b10100 '
#465500
0!
#466000
1!
b10101 '
#466500
0!
#467000
1!
b10110 '
#467500
0!
#468000
1!
b10111 '
#468500
0!
#469000
1!
b11000 '
#469500
0!
#470000
1!
b11001 '
#470500
0!
#471000
1!
b11010 '
#471500
0!
#472000
1!
b11011 '
#472500
0!
#473000
1!
b11100 '
#473500
0!
#474000
1!
b11101 '
#474500
0!
#475000
1!
b11110 '
#475500
0!
#476000
1!
b11111 '
#476500
0!
#477000
1!
b100000 '
#477500
0!
#478000
1!
b100001 '
#478500
0!
#479000
1!
b100010 '
#479500
0!
#480000
1!
b100011 '
#480500
0!
#481000
1!
b100100 '
#481500
0!
#482000
1!
b100101 '
#482500
0!
#483000
1!
b100110 '
#483500
0!
#484000
1!
b100111 '
#484500
0!
#485000
1!
b101000 '
#485500
0!
#486000
1!
b101001 '
#486500
0!
#487000
1!
b101010 '
#487500
0!
#488000
1!
b101011 '
#488500
0!
#489000
1!
b101100 '
#489500
0!
#490000
1!
b101101 '
#490500
0!
#491000
1!
b101110 '
#491500
0!
#492000
1!
b101111 '
#492500
0!
#493000
1!
b110000 '
#493500
0!
#494000
1!
b110001 '
#494500
0!
#495000
1!
b110010 '
#495500
0!
#496000
1!
b110011 '
#496500
0!
#497000
1!
b110100 '
#497500
0!
#498000
1!
b110101 '
#498500
0!
#499000
1!
b110110 '
#499500
0!
#500000
1!
b110111 '
#500500
0!
#501000
1!
b111000 '
#501500
0!
#502000
1!
b111001 '
#502500
0!
#503000
1!
b111010 '
#503500
0!
#504000
1!
b111011 '
#504500
0!
#505000
1!
b111100 '
#505500
0!
#506000
1!
b111101 '
#506500
0!
#507000
1!
b111110 '
#507500
0!
#508000
1!
b111111 '
#508500
0!
#509000
1!
b1000000 '
#509500
0!
#510000
1!
b1000001 '
#510500
0!
#511000
1!
b1000010 '
#511500
0!
#512000
1!
b1000011 '
#512500
0!
#513000
1!
b1000100 '
#513500
0!
#514000
1!
b1000101 '
#514500
0!
#515000
1!
b1000110 '
#515500
0!
#516000
1!
b1000111 '
#516500
0!
#517000
1!
b1001000 '
#517500
0!
#518000
1!
b1001001 '
#518500
0!
#519000
1!
b1001010 '
#519500
0!
#520000
1!
b1001011 '
#520500
0!
#521000
1!
b1001100 '
#521500
0!
#522000
1!
b1001101 '
#522500
0!
#523000
1!
b1001110 '
#523500
0!
#524000
1!
b1001111 '
#524500
0!
#525000
1!
b1010000 '
#525500
0!
#526000
1!
b1010001 '
#526500
0!
#527000
1!
b1010010 '
#527500
0!
#528000
1!
b1010011 '
#528500
0!
#529000
1!
b1010100 '
#529500
0!
#530000
1!
b1010101 '
#530500
0!
#531000
1!
b1010110 '
#531500
0!
#532000
1!
b1010111 '
#532500
0!
#533000
1!
b1011000 '
#533500
0!
#534000
1!
b1011001 '
#534500
0!
#535000
1!
b1011010 '
#535500
0!
#536000
1!
b1011011 '
#536500
0!
#537000
1!
b1011100 '
#537500
0!
#538000
1!
b1011101 '
#538500
0!
#539000
1!
b1011110 '
#539500
0!
#540000
1!
b1011111 '
#540500
0!
#541000
1!
b1100000 '
#541500
0!
#542000
1!
b1100001 '
#542500
0!
#543000
1!
b1100010 '
#543500
0!
#544000
1!
b1100011 '
#544500
0!
#545000
1!
b1100100 '
#545500
0!
#546000
1!
b1100101 '
#546500
0!
#547000
1!
b1100110 '
#547500
0!
#548000
1!
b1100111 '
#548500
0!
#549000
1!
b1101000 '
#549500
0!
#550000
1!
b1101001 '
#550500
0!
#551000
1!
b1101010 '
#551500
0!
#552000
1!
b1101011 '
#552500
0!
#553000
1!
b1101100 '
#553500
0!
#554000
1!
b1101101 '
#554500
0!
#555000
1!
b1101110 '
#555500
0!
#556000
1!
b1101111 '
#556500
0!
#557000
1!
b1110000 '
#557500
0!
#558000
1!
b1110001 '
#558500
0!
#559000
1!
b1110010 '
#559500
0!
#560000
1!
b1110011 '
#560500
0!
#561000
1!
b1110100 '
#561500
0!
#562000
1!
b1110101 '
#562500
0!
#563000
1!
b1110110 '
#563500
0!
#564000
1!
b1110111 '
#564500
0!
#565000
1!
b1111000 '
#565500
0!
#566000
1!
b1111001 '
#566500
0!
#567000
1!
b1111010 '
#567500
0!
#568000
1!
b1111011 '
#568500
0!
#569000
1!
b1111100 '
#569500
0!
#570000
1!
b1111101 '
#570500
0!
#571000
1!
b1111110 '
#571500
0!
#572000
1!
b1111111 '
#572500
0!
#573000
1!
b10000000 '
#573500
0!
#574000
1!
b10000001 '
#574500
0!
#575000
1!
b10000010 '
#575500
0!
#576000
1!
b10000011 '
#576500
0!
#577000
1!
b10000100 '
#577500
0!
#578000
1!
b10000101 '
#578500
0!
#579000
1!
b10000110 '
#579500
0!
#580000
1!
b10000111 '
#580500
0!
#581000
1!
b10001000 '
#581500
0!
#582000
1!
b10001001 '
#582500
0!
#583000
1!
b10001010 '
#583500
0!
#584000
1!
b10001011 '
#584500
0!
#585000
1!
b10001100 '
#585500
0!
#586000
1!
b10001101 '
#586500
0!
#587000
1!
b10001110 '
#587500
0!
#588000
1!
b10001111 '
#588500
0!
#589000
1!
b10010000 '
#589500
0!
#590000
1!
b10010001 '
#590500
0!
#591000
1!
b10010010 '
#591500
0!
#592000
1!
b10010011 '
#592500
0!
#593000
1!
b10010100 '
#593500
0!
#594000
1!
b10010101 '
#594500
0!
#595000
1!
b10010110 '
#595500
0!
#596000
1!
b10010111 '
#596500
0!
#597000
1!
b10011000 '
#597500
0!
#598000
1!
b10011001 '
#598500
0!
#599000
1!
b10011010 '
#599500
0!
#600000
1!
b10011011 '
#600500
0!
#601000
1!
b10011100 '
#601500
0!
#602000
1!
b10011101 '
#602500
0!
#603000
1!
b10011110 '
#603500
0!
#604000
1!
b10011111 '
#604500
0!
#605000
1!
b10100000 '
#605500
0!
#606000
1!
b10100001 '
#606500
0!
#607000
1!
b10100010 '
#607500
0!
#608000
1!
b10100011 '
#608500
0!
#609000
1!
b10100100 '
#609500
0!
#610000
1!
b10100101 '
#610500
0!
#611000
1!
b10100110 '
#611500
0!
#612000
1!
b10100111 '
#612500
0!
#613000
1!
b10101000 '
#613500
0!
#614000
1!
b10101001 '
#614500
0!
#615000
1!
b10101010 '
#615500
0!
#616000
1!
b10101011 '
#616500
0!
#617000
1!
b10101100 '
#617500
0!
#618000
1!
b10101101 '
#618500
0!
#619000
1!
b10101110 '
#619500
0!
#620000
1!
b10101111 '
#620500
0!
#621000
1!
b10110000 '
#621500
0!
#622000
1!
b10110001 '
#622500
0!
#623000
1!
b10110010 '
#623500
0!
#624000
1!
b10110011 '
#624500
0!
#625000
1!
b10110100 '
#625500
0!
#626000
1!
b10110101 '
#626500
0!
#627000
1!
b10110110 '
#627500
0!
#628000
1!
b10110111 '
#628500
0!
#629000
1!
b10111000 '
#629500
0!
#630000
1!
b10111001 '
#630500
0!
#631000
1!
b10111010 '
#631500
0!
#632000
1!
b10111011 '
#632500
0!
#633000
1!
b10111100 '
#633500
0!
#634000
1!
b10111101 '
#634500
0!
#635000
1!
b10111110 '
#635500
0!
#636000
1!
b10111111 '
#636500
0!
#637000
1!
b11000000 '
#637500
0!
#638000
1!
b11000001 '
#638500
0!
#639000
1!
b11000010 '
#639500
0!
#640000
1!
b11000011 '
#640500
0!
#641000
1!
b11000100 '
#641500
0!
#642000
1!
b11000101 '
#642500
0!
#643000
1!
b11000110 '
#643500
0!
#644000
1!
b11000111 '
#644500
0!
#645000
1!
b11001000 '
#645500
0!
#646000
1!
b11001001 '
#646500
0!
#647000
1!
b11001010 '
#647500
0!
#648000
1!
b11001011 '
#648500
0!
#649000
1!
b11001100 '
#649500
0!
#650000
1!
b11001101 '
#650500
0!
#651000
1!
b11001110 '
#651500
0!
#652000
1!
b11001111 '
#652500
0!
#653000
1!
b11010000 '
#653500
0!
#654000
1!
b11010001 '
#654500
0!
#655000
1!
b11010010 '
#655500
0!
#656000
1!
b11010011 '
#656500
0!
#657000
1!
b11010100 '
#657500
0!
#658000
1!
b11010101 '
#658500
0!
#659000
1!
b11010110 '
#659500
0!
#660000
1!
b11010111 '
#660500
0!
#661000
1!
b11011000 '
#661500
0!
#662000
1!
b11011001 '
#662500
0!
#663000
1!
b0 '
#663500
0!
#664000
1!
b1 '
#664500
0!
#665000
1!
b10 '
#665500
0!
#666000
1!
b11 '
#666500
0!
#667000
1!
b100 '
#667500
0!
#668000
1!
b101 '
#668500
0!
#669000
1!
b110 '
#669500
0!
#670000
1!
b111 '
#670500
0!
#671000
1!
b1000 '
#671500
0!
#672000
1!
b1001 '
#672500
0!
#673000
1!
b1010 '
#673500
0!
#674000
1!
b1011 '
#674500
0!
#675000
1!
b1100 '
#675500
0!
#676000
1!
b1101 '
#676500
0!
#677000
1!
b1110 '
#677500
0!
#678000
1!
b1111 '
#678500
0!
#679000
1!
b10000 '
#679500
0!
#680000
1!
b10001 '
#680500
0!
#681000
1!
b10010 '
#681500
0!
#682000
1!
b10011 '
#682500
0!
#683000
1!
b10100 '
#683500
0!
#684000
1!
b10101 '
#684500
0!
#685000
1!
b10110 '
#685500
0!
#686000
1!
b10111 '
#686500
0!
#687000
1!
b11000 '
#687500
0!
#688000
1!
b11001 '
#688500
0!
#689000
1!
b11010 '
#689500
0!
#690000
1!
b11011 '
#690500
0!
#691000
1!
b11100 '
#691500
0!
#692000
1!
b11101 '
#692500
0!
#693000
1!
b11110 '
#693500
0!
#694000
1!
b11111 '
#694500
0!
#695000
1!
b100000 '
#695500
0!
#696000
1!
b100001 '
#696500
0!
#697000
1!
b100010 '
#697500
0!
#698000
1!
b100011 '
#698500
0!
#699000
1!
b100100 '
#699500
0!
#700000
1!
b100101 '
#700500
0!
#701000
1!
b100110 '
#701500
0!
#702000
1!
b100111 '
#702500
0!
#703000
1!
b101000 '
#703500
0!
#704000
1!
b101001 '
#704500
0!
#705000
1!
b101010 '
#705500
0!
#706000
1!
b101011 '
#706500
0!
#707000
1!
b101100 '
#707500
0!
#708000
1!
b101101 '
#708500
0!
#709000
1!
b101110 '
#709500
0!
#710000
1!
b101111 '
#710500
0!
#711000
1!
b110000 '
#711500
0!
#712000
1!
b110001 '
#712500
0!
#713000
1!
b110010 '
#713500
0!
#714000
1!
b110011 '
#714500
0!
#715000
1!
b110100 '
#715500
0!
#716000
1!
b110101 '
#716500
0!
#717000
1!
b110110 '
#717500
0!
#718000
1!
b110111 '
#718500
0!
#719000
1!
b111000 '
#719500
0!
#720000
1!
b111001 '
#720500
0!
#721000
1!
b111010 '
#721500
0!
#722000
1!
b111011 '
#722500
0!
#723000
1!
b111100 '
#723500
0!
#724000
1!
b111101 '
#724500
0!
#725000
1!
b111110 '
#725500
0!
#726000
1!
b111111 '
#726500
0!
#727000
1!
b1000000 '
#727500
0!
#728000
1!
b1000001 '
#728500
0!
#729000
1!
b1000010 '
#729500
0!
#730000
1!
b1000011 '
#730500
0!
#731000
1!
b1000100 '
#731500
0!
#732000
1!
b1000101 '
#732500
0!
#733000
1!
b1000110 '
#733500
0!
#734000
1!
b1000111 '
#734500
0!
#735000
1!
b1001000 '
#735500
0!
#736000
1!
b1001001 '
#736500
0!
#737000
1!
b1001010 '
#737500
0!
#738000
1!
b1001011 '
#738500
0!
#739000
1!
b1001100 '
#739500
0!
#740000
1!
b1001101 '
#740500
0!
#741000
1!
b1001110 '
#741500
0!
#742000
1!
b1001111 '
#742500
0!
#743000
1!
b1010000 '
#743500
0!
#744000
1!
b1010001 '
#744500
0!
#745000
1!
b1010010 '
#745500
0!
#746000
1!
b1010011 '
#746500
0!
#747000
1!
b1010100 '
#747500
0!
#748000
1!
b1010101 '
#748500
0!
#749000
1!
b1010110 '
#749500
0!
#750000
1!
b1010111 '
#750500
0!
#751000
1!
b1011000 '
#751500
0!
#752000
1!
b1011001 '
#752500
0!
#753000
1!
b1011010 '
#753500
0!
#754000
1!
b1011011 '
#754500
0!
#755000
1!
b1011100 '
#755500
0!
#756000
1!
b1011101 '
#756500
0!
#757000
1!
b1011110 '
#757500
0!
#758000
1!
b1011111 '
#758500
0!
#759000
1!
b1100000 '
#759500
0!
#760000
1!
b1100001 '
#760500
0!
#761000
1!
b1100010 '
#761500
0!
#762000
1!
b1100011 '
#762500
0!
#763000
1!
b1100100 '
#763500
0!
#764000
1!
b1100101 '
#764500
0!
#765000
1!
b1100110 '
#765500
0!
#766000
1!
b1100111 '
#766500
0!
#767000
1!
b1101000 '
#767500
0!
#768000
1!
b1101001 '
#768500
0!
#769000
1!
b1101010 '
#769500
0!
#770000
1!
b1101011 '
#770500
0!
#771000
1!
b1101100 '
#771500
0!
#772000
1!
b1101101 '
#772500
0!
#773000
1!
b1101110 '
#773500
0!
#774000
1!
b1101111 '
#774500
0!
#775000
1!
b1110000 '
#775500
0!
#776000
1!
b1110001 '
#776500
0!
#777000
1!
b1110010 '
#777500
0!
#778000
1!
b1110011 '
#778500
0!
#779000
1!
b1110100 '
#779500
0!
#780000
1!
b1110101 '
#780500
0!
#781000
1!
b1110110 '
#781500
0!
#782000
1!
b1110111 '
#782500
0!
#783000
1!
b1111000 '
#783500
0!
#784000
1!
b1111001 '
#784500
0!
#785000
1!
b1111010 '
#785500
0!
#786000
1!
b1111011 '
#786500
0!
#787000
1!
b1111100 '
#787500
0!
#788000
1!
b1111101 '
#788500
0!
#789000
1!
b1111110 '
#789500
0!
#790000
1!
b1111111 '
#790500
0!
#791000
1!
b10000000 '
#791500
0!
#792000
1!
b10000001 '
